{
  "Disabled": false,
  "Testing": false,
  "ScheduledForDeletion": false,
  "InstalledFromUrl": "",
  "IsThirdParty": false,
  "EffectiveVersion": "2.0.0.0",
  "IsAvailableForTesting": false,
  "Author": "MidoriKami",
  "Name": "Mappy",
  "Punchline": "A more versatile ingame map",
  "Description": "Replaces the ingame map with an ImGui implementation with several additional features.",
  "Changelog": null,
  "Tags": [
    "utility"
  ],
  "CategoryTags": [
    "Utility",
    "Other"
  ],
  "IsHide": false,
  "InternalName": "Mappy",
  "AssemblyVersion": "2.0.0.0",
  "TestingAssemblyVersion": null,
  "IsTestingExclusive": false,
  "RepoUrl": "https://github.com/MidoriKami/Mappy",
  "ApplicableVersion": "any",
  "DalamudApiLevel": 8,
  "DownloadCount": 0,
  "LastUpdate": 0,
  "DownloadLinkInstall": null,
  "DownloadLinkUpdate": null,
  "DownloadLinkTesting": null,
  "LoadRequiredState": 0,
  "LoadSync": false,
  "LoadPriority": 0,
  "CanUnloadAsync": false,
  "SupportsProfiles": true,
  "ImageUrls": null,
  "IconUrl": null,
  "AcceptsFeedback": false,
  "FeedbackMessage": null,
  "_isDip17Plugin": false,
  "_Dip17Channel": null
}